polykin/__init__.py
polykin/copolymerization/__init__.py
polykin/copolymerization/binary.py
polykin/copolymerization/copodataset.py
polykin/copolymerization/fitting.py
polykin/copolymerization/multicomponent.py
polykin/copolymerization/penultimate.py
polykin/copolymerization/terminal.py
polykin/distributions/__init__.py
polykin/distributions/analyticaldistributions.py
polykin/distributions/base.py
polykin/distributions/datadistribution.py
polykin/distributions/gold.py
polykin/distributions/misc.py
polykin/distributions/sampledata.py
polykin/flow/__init__.py
polykin/flow/friction.py
polykin/flow/prv.py
polykin/flow/rheology.py
polykin/hmt/__init__.py
polykin/hmt/correlations.py
polykin/hmt/diffusion.py
polykin/hmt/hex.py
polykin/kinetics/__init__.py
polykin/kinetics/reaction.py
polykin/kinetics/coefficients/__init__.py
polykin/kinetics/coefficients/arrhenius.py
polykin/kinetics/coefficients/base.py
polykin/kinetics/coefficients/cldpropagation.py
polykin/kinetics/coefficients/cldtermination.py
polykin/kinetics/coefficients/eyring.py
polykin/kinetics/emulsion/__init__.py
polykin/kinetics/emulsion/nbar.py
polykin/math/__init__.py
polykin/math/special.py
polykin/math/derivatives/__init__.py
polykin/math/derivatives/ndiff.py
polykin/math/derivatives/ode.py
polykin/math/fixpoint/__init__.py
polykin/math/fixpoint/anderson.py
polykin/math/fixpoint/wegstein.py
polykin/math/misc/__init__.py
polykin/math/misc/filters.py
polykin/math/misc/jcr.py
polykin/math/roots/__init__.py
polykin/math/roots/results.py
polykin/math/roots/scalar.py
polykin/math/roots/vector.py
polykin/properties/__init__.py
polykin/properties/diffusion/__init__.py
polykin/properties/diffusion/liquid.py
polykin/properties/diffusion/vapor.py
polykin/properties/diffusion/vrentasduda.py
polykin/properties/equations/__init__.py
polykin/properties/equations/base.py
polykin/properties/equations/dippr.py
polykin/properties/equations/vapor_pressure.py
polykin/properties/equations/viscosity.py
polykin-0.6.0.dist-info/METADATA
polykin-0.6.0.dist-info/WHEEL
polykin-0.6.0.dist-info/licenses/LICENSE
polykin-0.6.0.dist-info/RECORD
