Metadata-Version: 2.4
Name: polykin
Version: 0.6.0
Summary: A polymerization kinetics library.
Project-URL: Homepage, https://hugomvale.github.io/polykin/
Project-URL: Source, https://github.com/HugoMVale/polykin
Project-URL: Documentation, https://hugomvale.github.io/polykin/
License: MIT License
License-File: LICENSE
Keywords: kinetics,polymer,polymerization,reaction
Classifier: License :: OSI Approved :: MIT License
Classifier: Operating System :: OS Independent
Classifier: Programming Language :: Python :: 3
Classifier: Topic :: Scientific/Engineering
Classifier: Topic :: Scientific/Engineering :: Chemistry
Requires-Python: >=3.10.0
Requires-Dist: matplotlib>=3.8
Requires-Dist: mpmath>=1.3.0
Requires-Dist: numba>=0.60.0
Requires-Dist: numpy>=1.26.4
Requires-Dist: odrpack>=0.3.5
Requires-Dist: pandas>=2.2.2
Requires-Dist: pydantic>=2.10.2
Requires-Dist: scipy>=1.13.1
